grelu/__init__.py
grelu/design.py
grelu/utils.py
grelu/variant.py
grelu/visualize.py
grelu/data/__init__.py
grelu/data/augment.py
grelu/data/dataset.py
grelu/data/preprocess.py
grelu/data/utils.py
grelu/interpret/__init__.py
grelu/interpret/modisco.py
grelu/interpret/motifs.py
grelu/interpret/score.py
grelu/interpret/simulate.py
grelu/io/__init__.py
grelu/io/bed.py
grelu/io/bigwig.py
grelu/io/fasta.py
grelu/io/genome.py
grelu/io/motifs.py
grelu/lightning/__init__.py
grelu/lightning/losses.py
grelu/lightning/metrics.py
grelu/model/__init__.py
grelu/model/blocks.py
grelu/model/heads.py
grelu/model/layers.py
grelu/model/models.py
grelu/model/position.py
grelu/model/trunks/__init__.py
grelu/model/trunks/borzoi.py
grelu/model/trunks/enformer.py
grelu/model/trunks/explainn.py
grelu/resources/__init__.py
grelu/resources/blacklists/encode/hg19-blacklist.v2.bed
grelu/resources/blacklists/encode/hg38-blacklist.v2.bed
grelu/resources/blacklists/encode/mm10-blacklist.v2.bed
grelu/resources/blacklists/mito_combined/hg19.full.blacklist.bed
grelu/resources/blacklists/mito_combined/hg19_mm10_c.full.blacklist.bed
grelu/resources/blacklists/mito_combined/hg38.full.blacklist.bed
grelu/resources/blacklists/mito_combined/mm10.full.blacklist.bed
grelu/resources/blacklists/mito_combined/mm9.full.blacklist.bed
grelu/resources/meme/H12CORE_meme_format.meme
grelu/resources/meme/H13CORE_meme_format.meme
grelu/resources/meme/jaspar_2024_consensus.meme
grelu/sequence/__init__.py
grelu/sequence/format.py
grelu/sequence/metrics.py
grelu/sequence/mutate.py
grelu/sequence/utils.py
grelu/transforms/__init__.py
grelu/transforms/label_transforms.py
grelu/transforms/prediction_transforms.py
grelu/transforms/seq_transforms.py
grelu-1.0.9.dist-info/licenses/LICENSE.txt
grelu-1.0.9.dist-info/METADATA
grelu-1.0.9.dist-info/WHEEL
grelu-1.0.9.dist-info/top_level.txt
grelu-1.0.9.dist-info/RECORD
