Metadata-Version: 2.4
Name: gReLU
Version: 1.0.9
Summary: gReLU is a python library to train, interpret, and apply deep learning models to DNA sequences
Home-page: https://github.com/Genentech/gReLU
Author: lal.avantika,eraslan.gokcen
Author-email: lal.avantika@gene.com
License: MIT
Project-URL: Documentation, https://github.com/Genentech/gReLU
Project-URL: Source, https://github.com/Genentech/gReLU
Platform: Linux
Classifier: Development Status :: 4 - Beta
Classifier: Programming Language :: Python
Requires-Python: >=3.8
License-File: LICENSE.txt
Requires-Dist: importlib-metadata
Requires-Dist: importlib-resources
Requires-Dist: wandb>=0.14
Requires-Dist: numpy
Requires-Dist: pandas
Requires-Dist: seaborn
Requires-Dist: matplotlib
Requires-Dist: plotnine>=0.8
Requires-Dist: anndata>=0.8
Requires-Dist: scikit-learn
Requires-Dist: torch>=2.0
Requires-Dist: pytorch-lightning>=2.0
Requires-Dist: torchmetrics>=1.1
Requires-Dist: modisco-lite>=2.2.1
Requires-Dist: biopython
Requires-Dist: enformer-pytorch
Requires-Dist: genomepy
Requires-Dist: bioframe>=0.4
Requires-Dist: captum==0.5.0
Requires-Dist: logomaker>=0.8
Requires-Dist: pyBigWig
Requires-Dist: ledidi
Requires-Dist: tangermeme>=0.5.0
Requires-Dist: memelite
Requires-Dist: pygenomeviz<=0.4.4
Requires-Dist: statsmodels>=0.11.1
Requires-Dist: pyjaspar>=3.0
Provides-Extra: testing
Requires-Dist: setuptools; extra == "testing"
Requires-Dist: pytest; extra == "testing"
Requires-Dist: pytest-cov; extra == "testing"
Dynamic: license-file
